img2gif/__init__.py
img2gif/__main__.py
img2gif/cli.py
img2gif/config.py
img2gif/converter.py
img2gif/exceptions.py
img2gif/types.py
imgif-0.2.0.dist-info/METADATA
imgif-0.2.0.dist-info/WHEEL
imgif-0.2.0.dist-info/entry_points.txt
imgif-0.2.0.dist-info/licenses/LICENSE
imgif-0.2.0.dist-info/RECORD
