Metadata-Version: 2.4
Name: imgif
Version: 0.2.0
Summary: 🎬 A playful Python library for converting image sequences into animated GIFs
Project-URL: Homepage, https://github.com/atick-faisal/img2gif
Project-URL: Documentation, https://imgif.readthedocs.io
Project-URL: Repository, https://github.com/atick-faisal/img2gif
Project-URL: Issues, https://github.com/atick-faisal/img2gif/issues
Author-email: Atick Faisal <atickfaisal@gmail.com>
License: MIT
License-File: LICENSE
Keywords: animation,converter,gif,image,pillow
Classifier: Development Status :: 3 - Alpha
Classifier: Intended Audience :: Developers
Classifier: License :: OSI Approved :: MIT License
Classifier: Programming Language :: Python :: 3
Classifier: Programming Language :: Python :: 3.9
Classifier: Programming Language :: Python :: 3.10
Classifier: Programming Language :: Python :: 3.11
Classifier: Programming Language :: Python :: 3.12
Classifier: Programming Language :: Python :: 3.13
Classifier: Topic :: Multimedia :: Graphics
Classifier: Topic :: Software Development :: Libraries :: Python Modules
Requires-Python: >=3.9
Requires-Dist: click>=8.1.0
Requires-Dist: pillow>=10.0.0
Requires-Dist: rich>=13.7.0
Provides-Extra: dev
Requires-Dist: hatch>=1.9.0; extra == 'dev'
Requires-Dist: pre-commit>=3.5.0; extra == 'dev'
Requires-Dist: pytest-cov>=4.1.0; extra == 'dev'
Requires-Dist: pytest>=7.4.0; extra == 'dev'
Requires-Dist: ruff>=0.1.0; extra == 'dev'
Provides-Extra: docs
Requires-Dist: mkdocs-material>=9.4.0; extra == 'docs'
Requires-Dist: mkdocs>=1.5.0; extra == 'docs'
Requires-Dist: pymdown-extensions>=10.3.0; extra == 'docs'
